README.md
setup.py
mysqlcp/__init__.py
mysqlcp/__main__.py
mysqlcp.egg-info/PKG-INFO
mysqlcp.egg-info/SOURCES.txt
mysqlcp.egg-info/dependency_links.txt
mysqlcp.egg-info/entry_points.txt
mysqlcp.egg-info/requires.txt
mysqlcp.egg-info/top_level.txt