Metadata-Version: 2.1
Name: mysqlcp
Version: 1.0.0
Summary: Simple, secure and advanced module to perform safe MySQL queries
Home-page: https://github.com/AlaBouali/mysqlcp
Author: AlaBouali
Author-email: trap.leader.123@gmail.com
License: MIT License
Platform: UNKNOWN
Classifier: Programming Language :: Python
Classifier: License :: OSI Approved :: MIT License 
Requires-Python: >=2.7
